sql_repository/__init__.py
sql_repository/sql_repository.py
sql_repository/utils.py
sql_repository/version.py
tests/__init__.py
tests/test_utils.py
sql_repository-0.0.4.dist-info/METADATA
sql_repository-0.0.4.dist-info/WHEEL
sql_repository-0.0.4.dist-info/top_level.txt
sql_repository-0.0.4.dist-info/RECORD
